{"cameraMode":{"drawMode":0,"name":"Shaded","section":"Shading Mode"},"sceneLighting":false,"audioPlay":false,"sceneViewState":{"showFog":true,"showMaterialUpdate":false,"showSkybox":false,"showFlares":true,"showImageEffects":true,"showParticleSystems":true},"in2DMode":false,"pivot":{"x":29.262371063232423,"y":37.16261291503906,"z":-16.612136840820314},"rotation":{"x":0.0009254991891793907,"y":0.9962666630744934,"z":-0.08570036292076111,"w":0.010760785080492497},"size":99.14619445800781,"orthographic":false}